pgetopt/__init__.py
pgetopt_jyrgenn-2024.206.1405.dist-info/METADATA
pgetopt_jyrgenn-2024.206.1405.dist-info/WHEEL
pgetopt_jyrgenn-2024.206.1405.dist-info/top_level.txt
pgetopt_jyrgenn-2024.206.1405.dist-info/RECORD
