Metadata-Version: 2.1
Name: pgetopt-jyrgenn
Version: 2024.206.1405
Summary: THIS PACKAGE IS OBSOLETED by jpylib-jyrgenn.
Home-page: https://git.w21.org/python_modules/pgetopt
Author: Juergen Nickelsen
Author-email: ni@w21.org
License: UNKNOWN
Project-URL: Documentation, https://git.w21.org/python_modules/pgetopt/-/blob/v2024.206.1405/README.md
Project-URL: Source, https://git.w21.org/python_modules/pgetopt
Platform: UNKNOWN
Classifier: Programming Language :: Python :: 3
Classifier: License :: OSI Approved :: BSD License
Classifier: Operating System :: OS Independent
Requires-Python: >=3.5
